blocky/__init__.py
blocky/base.py
blocky/django/__init__.py
blocky/django/shortcuts.py
blocky/flask/__init__.py
blocky/flask/shortcuts.py
blocky-0.0.2.dist-info/DESCRIPTION.rst
blocky-0.0.2.dist-info/METADATA
blocky-0.0.2.dist-info/metadata.json
blocky-0.0.2.dist-info/pbr.json
blocky-0.0.2.dist-info/RECORD
blocky-0.0.2.dist-info/top_level.txt
blocky-0.0.2.dist-info/WHEEL
