Metadata-Version: 2.0
Name: blocky
Version: 0.0.2
Summary: Block rendering for flask and django using jinja2.
Home-page: https://github.com/OpenPixel/blocky
Author: Cameron A. Stitt
Author-email: cameron@cam.st
License: BSD
Keywords: flask jinja2 django
Platform: any
Classifier: Development Status :: 3 - Alpha
Classifier: Intended Audience :: Developers
Classifier: Topic :: Software Development :: Libraries :: Python Modules
Classifier: Programming Language :: Python
Requires-Dist: jinja2
Requires-Dist: flask
Requires-Dist: django
